{"code":0,"message":"0","ttl":1,"data":{"config":{"showadmin":1,"showentry":1,"showfloor":1},"hots":[{"rpid":1311531294,"oid":41025837,"type":1,"mid":22647292,"root":0,"parent":0,"dialog":0,"count":258,"rcount":252,"floor":218,"state":0,"fansgrade":0,"attr":0,"ctime":1547790339,"rpid_str":"1311531294","root_str":"0","parent_str":"0","dialog_str":"","like":3799,"action":0,"member":{"mid":"22647292","uname":"星月吖x","sex":"女","sign":"这里是星月，永远的拉拉人。想成为一位大家喜欢的up主，会努力的！随缘录特底屏，以后会投稿宅舞和游戏视频！\nQQ896333297","avatar":"http://i2.hdslb.com/bfs/face/124d3cf01add72187381bb91deb7985dcded8a17.jpg","rank":"10000","DisplayRank":"0","level_info":{"current_level":5,"current_min":0,"current_exp":0,"next_exp":0},"pendant":{"pid":0,"name":"","image":"","expire":0},"nameplate":{"nid":4,"name":"青铜殿堂","image":"http://i1.hdslb.com/bfs/face/2879cd5fb8518f7c6da75887994c1b2a7fe670bd.png","image_small":"http://i2.hdslb.com/bfs/face/6707c120e00a3445933308fd9b7bd9fad99e9ec4.png","level":"普通勋章","condition":"单个自制视频总播放数\u003e=1万"},"official_verify":{"type":-1,"desc":""},"vip":{"vipType":1,"vipDueDate":1515686400000,"dueRemark":"","accessStatus":0,"vipStatus":0,"vipStatusWarn":""},"fans_detail":null,"following":0},"content":{"message":"可能只有我还分不清五个姐妹。\n动画党看着弹幕刷xx天下第一。\n脑子里一直在想，这是谁。那又是谁。","plat":2,"device":"","members":[]},"replies":[{"rpid":1311534591,"oid":41025837,"type":1,"mid":28727227,"root":1311531294,"parent":1311531294,"dialog":1311534591,"count":0,"rcount":0,"floor":1,"state":0,"fansgrade":0,"attr":0,"ctime":1547790466,"rpid_str":"1311534591","root_str":"1311531294","parent_str":"1311531294","dialog_str":"","like":1025,"action":0,"member":{"mid":"28727227","uname":"阅微草堂-笔记","sex":"男","sign":"原名一一《阅微笔记》\n原作者一一纪昀-[清]","avatar":"http://i2.hdslb.com/bfs/face/0ec42289dd92ea1f0fdceaf737437ad1feba7f05.jpg","rank":"10000","DisplayRank":"0","level_info":{"current_level":5,"current_min":0,"current_exp":0,"next_exp":0},"pendant":{"pid":233,"name":"刺客伍六七","image":"http://i1.hdslb.com/bfs/face/b8a480b0f74935ca3146975f6591346d888669e3.png","expire":1585411200},"nameplate":{"nid":0,"name":"","image":"","image_small":"","level":"","condition":""},"official_verify":{"type":-1,"desc":""},"vip":{"vipType":2,"vipDueDate":1585411200000,"dueRemark":"","accessStatus":0,"vipStatus":1,"vipStatusWarn":""},"fans_detail":null,"following":0},"content":{"message":"你有成为男主的潜质","plat":2,"device":"","members":[]},"replies":null,"assist":0,"folder":{"has_folded":false,"is_folded":false,"rule":""}},{"rpid":1311543301,"oid":41025837,"type":1,"mid":180297752,"root":1311531294,"parent":1311531294,"dialog":1311543301,"count":0,"rcount":0,"floor":2,"state":0,"fansgrade":0,"attr":0,"ctime":1547790608,"rpid_str":"1311543301","root_str":"1311531294","parent_str":"1311531294","dialog_str":"","like":341,"action":0,"member":{"mid":"180297752","uname":"没有尽头的游戏","sex":"保密","sign":"过于温柔的世界呢","avatar":"http://i0.hdslb.com/bfs/face/ee26dbb40d6536a95c68d9f8f6c9d433bdebe5d3.jpg","rank":"10000","DisplayRank":"0","level_info":{"current_level":4,"current_min":0,"current_exp":0,"next_exp":0},"pendant":{"pid":0,"name":"","image":"","expire":0},"nameplate":{"nid":0,"name":"","image":"","image_small":"","level":"","condition":""},"official_verify":{"type":-1,"desc":""},"vip":{"vipType":2,"vipDueDate":1579017600000,"dueRemark":"","accessStatus":0,"vipStatus":1,"vipStatusWarn":""},"fans_detail":null,"following":0},"content":{"message":"你有成为男主的潜质","plat":2,"device":"","members":[]},"replies":null,"assist":0,"folder":{"has_folded":false,"is_folded":false,"rule":""}},{"rpid":1311545775,"oid":41025837,"type":1,"mid":19151485,"root":1311531294,"parent":1311531294,"dialog":1311545775,"count":0,"rcount":0,"floor":3,"state":0,"fansgrade":0,"attr":0,"ctime":1547790691,"rpid_str":"1311545775","root_str":"1311531294","parent_str":"1311531294","dialog_str":"","like":306,"action":0,"member":{"mid":"19151485","uname":"CraZy狂战","sex":"保密","sign":"","avatar":"http://i0.hdslb.com/bfs/face/36f443953930ab945c498f8f91b8214af558c864.jpg","rank":"10000","DisplayRank":"0","level_info":{"current_level":5,"current_min":0,"current_exp":0,"next_exp":0},"pendant":{"pid":0,"name":"","image":"","expire":0},"nameplate":{"nid":0,"name":"","image":"","image_small":"","level":"","condition":""},"official_verify":{"type":-1,"desc":""},"vip":{"vipType":2,"vipDueDate":1591804800000,"dueRemark":"","accessStatus":0,"vipStatus":1,"vipStatusWarn":""},"fans_detail":null,"following":0},"content":{"message":"你有成为男主的潜质","plat":2,"device":"","members":[]},"replies":null,"assist":0,"folder":{"has_folded":false,"is_folded":false,"rule":""}}],"assist":0,"folder":{"has_folded":false,"is_folded":false,"rule":"https://www.bilibili.com/blackboard/foldingreply.html"}},{"rpid":1311528905,"oid":41025837,"type":1,"mid":350290233,"root":0,"parent":0,"dialog":0,"count":110,"rcount":104,"floor":145,"state":0,"fansgrade":0,"attr":0,"ctime":1547790238,"rpid_str":"1311528905","root_str":"0","parent_str":"0","dialog_str":"","like":3710,"action":0,"member":{"mid":"350290233","uname":"靠脸吃饭喵某人","sex":"男","sign":"这是一位喜欢娜娜奇的评论区up主，确定不点个关注吗，呜喵～","avatar":"http://i0.hdslb.com/bfs/face/b20192c2f99a8fa0994fc127091dd4e1b7800201.jpg","rank":"10000","DisplayRank":"0","level_info":{"current_level":3,"current_min":0,"current_exp":0,"next_exp":0},"pendant":{"pid":0,"name":"","image":"","expire":0},"nameplate":{"nid":0,"name":"","image":"","image_small":"","level":"","condition":""},"official_verify":{"type":-1,"desc":""},"vip":{"vipType":2,"vipDueDate":1570377600000,"dueRemark":"","accessStatus":0,"vipStatus":1,"vipStatusWarn":""},"fans_detail":null,"following":0},"content":{"message":"一月治愈新番:约定的梦幻岛","plat":2,"device":"","members":[]},"replies":[{"rpid":1311530778,"oid":41025837,"type":1,"mid":31958221,"root":1311528905,"parent":1311528905,"dialog":1311530778,"count":0,"rcount":0,"floor":1,"state":0,"fansgrade":0,"attr":0,"ctime":1547790319,"rpid_str":"1311530778","root_str":"1311528905","parent_str":"1311528905","dialog_str":"","like":22,"action":0,"member":{"mid":"31958221","uname":"一_一透明物","sex":"男","sign":"随缘抢热评","avatar":"http://i1.hdslb.com/bfs/face/dec7a7d6ec556d0a251c2efb3f600ab3ad890685.jpg","rank":"10000","DisplayRank":"0","level_info":{"current_level":4,"current_min":0,"current_exp":0,"next_exp":0},"pendant":{"pid":0,"name":"","image":"","expire":0},"nameplate":{"nid":74,"name":"大会员2018年度勋章","image":"http://i2.hdslb.com/bfs/face/421179426c929dfeaed4117461c83f5d07ffb148.png","image_small":"http://i0.hdslb.com/bfs/face/682001c2e1c2ae887bdf2a0e18eef61180c48f84.png","level":"稀有勋章","condition":"2018.6.26-7.8某一天是年度大会员"},"official_verify":{"type":-1,"desc":""},"vip":{"vipType":2,"vipDueDate":1589385600000,"dueRemark":"","accessStatus":0,"vipStatus":1,"vipStatusWarn":""},"fans_detail":null,"following":0},"content":{"message":"你是魔鬼吗","plat":2,"device":"","members":[]},"replies":null,"assist":0,"folder":{"has_folded":false,"is_folded":false,"rule":""}},{"rpid":1311531837,"oid":41025837,"type":1,"mid":281136477,"root":1311528905,"parent":1311528905,"dialog":1311531837,"count":0,"rcount":0,"floor":2,"state":0,"fansgrade":0,"attr":0,"ctime":1547790359,"rpid_str":"1311531837","root_str":"1311528905","parent_str":"1311528905","dialog_str":"","like":6,"action":0,"member":{"mid":"281136477","uname":"好丽友Gentleman","sex":"男","sign":"QQ:2638 906 796\n有什么事都可以私聊!","avatar":"http://i0.hdslb.com/bfs/face/0294b102ae895b5df4190d683c0168f30ed3a313.jpg","rank":"10000","DisplayRank":"0","level_info":{"current_level":3,"current_min":0,"current_exp":0,"next_exp":0},"pendant":{"pid":0,"name":"","image":"","expire":0},"nameplate":{"nid":0,"name":"","image":"","image_small":"","level":"","condition":""},"official_verify":{"type":-1,"desc":""},"vip":{"vipType":2,"vipDueDate":1578240000000,"dueRemark":"","accessStatus":0,"vipStatus":1,"vipStatusWarn":""},"fans_detail":null,"following":0},"content":{"message":"啊♂","plat":2,"device":"","members":[]},"replies":null,"assist":0,"folder":{"has_folded":false,"is_folded":false,"rule":""}},{"rpid":1311532776,"oid":41025837,"type":1,"mid":62482889,"root":1311528905,"parent":1311528905,"dialog":1311532776,"count":0,"rcount":0,"floor":3,"state":0,"fansgrade":0,"attr":0,"ctime":1547790395,"rpid_str":"1311532776","root_str":"1311528905","parent_str":"1311528905","dialog_str":"","like":2,"action":0,"member":{"mid":"62482889","uname":"-薏苓-","sex":"保密","sign":"『为你，千千万万遍』","avatar":"http://i2.hdslb.com/bfs/face/d5e5b67052d141977132c5c8c37f2107d8e5bc07.jpg","rank":"10000","DisplayRank":"0","level_info":{"current_level":4,"current_min":0,"current_exp":0,"next_exp":0},"pendant":{"pid":0,"name":"","image":"","expire":0},"nameplate":{"nid":0,"name":"","image":"","image_small":"","level":"","condition":""},"official_verify":{"type":-1,"desc":""},"vip":{"vipType":1,"vipDueDate":1529510400000,"dueRemark":"","accessStatus":0,"vipStatus":0,"vipStatusWarn":""},"fans_detail":null,"following":0},"content":{"message":"魔鬼本鬼","plat":2,"device":"","members":[]},"replies":null,"assist":0,"folder":{"has_folded":false,"is_folded":false,"rule":""}}],"assist":0,"folder":{"has_folded":false,"is_folded":false,"rule":"https://www.bilibili.com/blackboard/foldingreply.html"}},{"rpid":1311585165,"oid":41025837,"type":1,"mid":10310702,"root":0,"parent":0,"dialog":0,"count":51,"rcount":50,"floor":600,"state":0,"fansgrade":0,"attr":0,"ctime":1547792155,"rpid_str":"1311585165","root_str":"0","parent_str":"0","dialog_str":"","like":1649,"action":0,"member":{"mid":"10310702","uname":"可意KeyI","sex":"保密","sign":"时间真是太快了","avatar":"http://i0.hdslb.com/bfs/face/7ef5edfab2a40b31744d15440412ebe7a6516c44.jpg","rank":"10000","DisplayRank":"0","level_info":{"current_level":6,"current_min":0,"current_exp":0,"next_exp":0},"pendant":{"pid":0,"name":"","image":"","expire":0},"nameplate":{"nid":6,"name":"高级搬运工","image":"http://i2.hdslb.com/bfs/face/a9af39ab7ed08e078c45d58dd96a6411aba1a9d3.png","image_small":"http://i0.hdslb.com/bfs/face/46e5aae4667c72c379b46b51fac4b4426d9214e7.png","level":"高级勋章","condition":"转载视频投稿通过总数\u003e=100"},"official_verify":{"type":-1,"desc":""},"vip":{"vipType":2,"vipDueDate":1629302400000,"dueRemark":"","accessStatus":0,"vipStatus":1,"vipStatusWarn":""},"fans_detail":null,"following":0},"content":{"message":"炒什么一花二乃三玖四叶五月六小龄童的股啊，\n真是幼稚！要炒就炒OP股，多罗罗OP牛逼！\n……\n对了，三玖天下第一！（滑稽）","plat":1,"device":"","members":[]},"replies":[{"rpid":1311595404,"oid":41025837,"type":1,"mid":25191995,"root":1311585165,"parent":1311585165,"dialog":1311595404,"count":0,"rcount":0,"floor":1,"state":0,"fansgrade":0,"attr":0,"ctime":1547792401,"rpid_str":"1311595404","root_str":"1311585165","parent_str":"1311585165","dialog_str":"","like":41,"action":0,"member":{"mid":"25191995","uname":"36D路飞","sex":"保密","sign":"好烂，好懒，好麻烦","avatar":"http://i1.hdslb.com/bfs/face/dccb6078fdf9b60df2d4a2d3df284161cffa1c3a.jpg","rank":"10000","DisplayRank":"0","level_info":{"current_level":5,"current_min":0,"current_exp":0,"next_exp":0},"pendant":{"pid":0,"name":"","image":"","expire":0},"nameplate":{"nid":0,"name":"","image":"","image_small":"","level":"","condition":""},"official_verify":{"type":-1,"desc":""},"vip":{"vipType":2,"vipDueDate":1558022400000,"dueRemark":"","accessStatus":0,"vipStatus":1,"vipStatusWarn":""},"fans_detail":null,"following":0},"content":{"message":"家有女友有话要说","plat":2,"device":"","members":[]},"replies":null,"assist":0,"folder":{"has_folded":false,"is_folded":false,"rule":""}},{"rpid":1311597348,"oid":41025837,"type":1,"mid":168643293,"root":1311585165,"parent":1311585165,"dialog":1311597348,"count":0,"rcount":0,"floor":2,"state":0,"fansgrade":0,"attr":0,"ctime":1547792492,"rpid_str":"1311597348","root_str":"1311585165","parent_str":"1311585165","dialog_str":"","like":88,"action":0,"member":{"mid":"168643293","uname":"章口就莱六学家","sex":"男","sign":"","avatar":"http://i2.hdslb.com/bfs/face/c0be1f63e82b90f5921e255e0b28d1591ba4befc.jpg","rank":"10000","DisplayRank":"0","level_info":{"current_level":4,"current_min":0,"current_exp":0,"next_exp":0},"pendant":{"pid":0,"name":"","image":"","expire":0},"nameplate":{"nid":61,"name":"饭圈楷模","image":"http://i0.hdslb.com/bfs/face/5a90f715451325c642a6ac39e01195cb6d075734.png","image_small":"http://i2.hdslb.com/bfs/face/5bfc1b4fb3f4b411495dddb0b2127ad80f6fbcac.png","level":"普通勋章","condition":"当前持有粉丝勋章最高等级\u003e=10级"},"official_verify":{"type":-1,"desc":""},"vip":{"vipType":0,"vipDueDate":0,"dueRemark":"","accessStatus":0,"vipStatus":0,"vipStatusWarn":""},"fans_detail":null,"following":0},"content":{"message":"混进了什么奇怪的东西(｀・ω・´)","plat":2,"device":"","members":[]},"replies":null,"assist":0,"folder":{"has_folded":false,"is_folded":false,"rule":""}},{"rpid":1311606128,"oid":41025837,"type":1,"mid":35677809,"root":1311585165,"parent":1311585165,"dialog":1311606128,"count":0,"rcount":0,"floor":3,"state":0,"fansgrade":0,"attr":0,"ctime":1547792873,"rpid_str":"1311606128","root_str":"1311585165","parent_str":"1311585165","dialog_str":"","like":243,"action":0,"member":{"mid":"35677809","uname":"碧磷蛇","sex":"保密","sign":"猫宫日向\n的勋章哒\nwryyyyyy","avatar":"http://i0.hdslb.com/bfs/face/f5867d5423e5479a0df67120c9f79e58e0ea1b40.jpg","rank":"10000","DisplayRank":"0","level_info":{"current_level":4,"current_min":0,"current_exp":0,"next_exp":0},"pendant":{"pid":268,"name":"2018","image":"http://i0.hdslb.com/bfs/face/44352a61e8f63ce17b33be9e024823c25cd2ca3f.png","expire":1550146088},"nameplate":{"nid":0,"name":"","image":"","image_small":"","level":"","condition":""},"official_verify":{"type":-1,"desc":""},"vip":{"vipType":0,"vipDueDate":0,"dueRemark":"","accessStatus":0,"vipStatus":0,"vipStatusWarn":""},"fans_detail":null,"following":0},"content":{"message":"混进了五个奇怪的东西","plat":2,"device":"","members":[]},"replies":null,"assist":0,"folder":{"has_folded":false,"is_folded":false,"rule":""}}],"assist":0,"folder":{"has_folded":false,"is_folded":false,"rule":"https://www.bilibili.com/blackboard/foldingreply.html"}}],"notice":null,"page":{"acount":3428,"count":2154,"num":58,"size":20},"replies":[{"rpid":1311763685,"oid":41025837,"type":1,"mid":12709022,"root":0,"parent":0,"dialog":0,"count":0,"rcount":0,"floor":1060,"state":0,"fansgrade":0,"attr":0,"ctime":1547799063,"rpid_str":"1311763685","root_str":"0","parent_str":"0","dialog_str":"","like":0,"action":0,"member":{"mid":"12709022","uname":"缺失的世界","sex":"男","sign":"任心为人，当然也有原则。","avatar":"http://i1.hdslb.com/bfs/face/d9c527562655f75a9c714e618e0df8681775c02b.jpg","rank":"10000","DisplayRank":"0","level_info":{"current_level":4,"current_min":0,"current_exp":0,"next_exp":0},"pendant":{"pid":153,"name":"citrus","image":"http://i2.hdslb.com/bfs/face/f2d3a85b611eb2ef13cb64415187e3e9fd487ec8.png","expire":1555257600},"nameplate":{"nid":0,"name":"","image":"","image_small":"","level":"","condition":""},"official_verify":{"type":-1,"desc":""},"vip":{"vipType":2,"vipDueDate":1555257600000,"dueRemark":"","accessStatus":0,"vipStatus":1,"vipStatusWarn":""},"fans_detail":null,"following":0},"content":{"message":"喜欢阳菜","plat":2,"device":"","members":[]},"replies":null,"assist":0,"folder":{"has_folded":false,"is_folded":false,"rule":"https://www.bilibili.com/blackboard/foldingreply.html"}},{"rpid":1311763670,"oid":41025837,"type":1,"mid":15264430,"root":0,"parent":0,"dialog":0,"count":0,"rcount":0,"floor":1059,"state":0,"fansgrade":0,"attr":0,"ctime":1547799062,"rpid_str":"1311763670","root_str":"0","parent_str":"0","dialog_str":"","like":0,"action":0,"member":{"mid":"15264430","uname":"小红帽鲁比","sex":"保密","sign":"有一个夜晚我烧毁了所有的记忆，从此我的梦就透明了；有一个早晨我扔掉了所有的昨天，从此我的脚步就轻盈了","avatar":"http://i0.hdslb.com/bfs/face/b2deefb410cae53d1a5835dd8e12a8110e81ffbd.jpg","rank":"10000","DisplayRank":"0","level_info":{"current_level":4,"current_min":0,"current_exp":0,"next_exp":0},"pendant":{"pid":0,"name":"","image":"","expire":0},"nameplate":{"nid":0,"name":"","image":"","image_small":"","level":"","condition":""},"official_verify":{"type":-1,"desc":""},"vip":{"vipType":1,"vipDueDate":1513267200000,"dueRemark":"","accessStatus":0,"vipStatus":0,"vipStatusWarn":""},"fans_detail":null,"following":0},"content":{"message":"中间炸出来一堆影之诗玩家","plat":1,"device":"","members":[]},"replies":null,"assist":0,"folder":{"has_folded":false,"is_folded":false,"rule":"https://www.bilibili.com/blackboard/foldingreply.html"}},{"rpid":1311763228,"oid":41025837,"type":1,"mid":226903908,"root":0,"parent":0,"dialog":0,"count":0,"rcount":0,"floor":1058,"state":0,"fansgrade":0,"attr":0,"ctime":1547799043,"rpid_str":"1311763228","root_str":"0","parent_str":"0","dialog_str":"","like":0,"action":0,"member":{"mid":"226903908","uname":"杰哥buyao","sex":"保密","sign":"","avatar":"http://i2.hdslb.com/bfs/face/87cd197597582379531ea6e356b4ec9c291bf68a.jpg","rank":"10000","DisplayRank":"0","level_info":{"current_level":3,"current_min":0,"current_exp":0,"next_exp":0},"pendant":{"pid":0,"name":"","image":"","expire":0},"nameplate":{"nid":37,"name":"好人卡","image":"http://i2.hdslb.com/bfs/face/1be8854328a497ff20a3538b4961bf1436f6b843.png","image_small":"http://i1.hdslb.com/bfs/face/1be8854328a497ff20a3538b4961bf1436f6b843.png","level":"高级勋章","condition":"直播用户等级\u003e=30级"},"official_verify":{"type":-1,"desc":""},"vip":{"vipType":1,"vipDueDate":1549900800000,"dueRemark":"","accessStatus":0,"vipStatus":1,"vipStatusWarn":""},"fans_detail":null,"following":0},"content":{"message":"直球营业喜欢","plat":2,"device":"","members":[]},"replies":null,"assist":0,"folder":{"has_folded":false,"is_folded":false,"rule":"https://www.bilibili.com/blackboard/foldingreply.html"}},{"rpid":1311762878,"oid":41025837,"type":1,"mid":34301271,"root":0,"parent":0,"dialog":0,"count":0,"rcount":0,"floor":1057,"state":0,"fansgrade":1,"attr":0,"ctime":1547799027,"rpid_str":"1311762878","root_str":"0","parent_str":"0","dialog_str":"","like":0,"action":0,"member":{"mid":"34301271","uname":"你们的故友","sex":"保密","sign":"即使看到的只是背影 心中也会感动一丝温暖","avatar":"http://i0.hdslb.com/bfs/face/1d72d26341cee3994ae3ab4d9e79be7d5870c0b6.jpg","rank":"10000","DisplayRank":"0","level_info":{"current_level":5,"current_min":0,"current_exp":0,"next_exp":0},"pendant":{"pid":276,"name":"中野三玖","image":"http://i0.hdslb.com/bfs/face/fd4a04100e7bdd68716592e4c68d55ac2a4e21c2.png","expire":1548435024},"nameplate":{"nid":57,"name":"收集萌新","image":"http://i1.hdslb.com/bfs/face/7767275600ea63d351b22fa87ec15a79aa24e5e5.png","image_small":"http://i2.hdslb.com/bfs/face/6589d992655595bf51543f268040eaeaed372fae.png","level":"普通勋章","condition":"同时拥有粉丝勋章\u003e=5个"},"official_verify":{"type":-1,"desc":""},"vip":{"vipType":0,"vipDueDate":0,"dueRemark":"","accessStatus":0,"vipStatus":0,"vipStatusWarn":""},"fans_detail":{"uid":34301271,"medal_id":2226,"medal_name":"泛团","score":0,"level":3,"intimacy":0,"master_status":1,"is_receive":1},"following":0},"content":{"message":"啥时候做·mad呀","plat":1,"device":"","members":[]},"replies":null,"assist":0,"folder":{"has_folded":false,"is_folded":false,"rule":"https://www.bilibili.com/blackboard/foldingreply.html"}},{"rpid":1311762252,"oid":41025837,"type":1,"mid":9943131,"root":0,"parent":0,"dialog":0,"count":0,"rcount":0,"floor":1056,"state":0,"fansgrade":0,"attr":0,"ctime":1547798997,"rpid_str":"1311762252","root_str":"0","parent_str":"0","dialog_str":"","like":0,"action":0,"member":{"mid":"9943131","uname":"买买提之刃","sex":"男","sign":"今日槿花落，明朝桐树秋","avatar":"http://i2.hdslb.com/bfs/face/5b393f8e7e8697a248b2b9d5c24ee1cbd03a192e.jpg","rank":"10000","DisplayRank":"0","level_info":{"current_level":4,"current_min":0,"current_exp":0,"next_exp":0},"pendant":{"pid":0,"name":"","image":"","expire":0},"nameplate":{"nid":0,"name":"","image":"","image_small":"","level":"","condition":""},"official_verify":{"type":-1,"desc":""},"vip":{"vipType":2,"vipDueDate":1559923200000,"dueRemark":"","accessStatus":0,"vipStatus":1,"vipStatusWarn":""},"fans_detail":null,"following":0},"content":{"message":"UP主你真他么是个鬼才","plat":1,"device":"","members":[]},"replies":null,"assist":0,"folder":{"has_folded":false,"is_folded":false,"rule":"https://www.bilibili.com/blackboard/foldingreply.html"}},{"rpid":1311760169,"oid":41025837,"type":1,"mid":5283561,"root":0,"parent":0,"dialog":0,"count":0,"rcount":0,"floor":1055,"state":0,"fansgrade":0,"attr":0,"ctime":1547798901,"rpid_str":"1311760169","root_str":"0","parent_str":"0","dialog_str":"","like":0,"action":0,"member":{"mid":"5283561","uname":"永鑫新","sex":"男","sign":"","avatar":"http://i0.hdslb.com/bfs/face/da06c408d0e6b1285f48d767c995629709a26d64.jpg","rank":"10000","DisplayRank":"0","level_info":{"current_level":5,"current_min":0,"current_exp":0,"next_exp":0},"pendant":{"pid":0,"name":"","image":"","expire":0},"nameplate":{"nid":57,"name":"收集萌新","image":"http://i2.hdslb.com/bfs/face/7767275600ea63d351b22fa87ec15a79aa24e5e5.png","image_small":"http://i2.hdslb.com/bfs/face/6589d992655595bf51543f268040eaeaed372fae.png","level":"普通勋章","condition":"同时拥有粉丝勋章\u003e=5个"},"official_verify":{"type":-1,"desc":""},"vip":{"vipType":1,"vipDueDate":1548345600000,"dueRemark":"","accessStatus":0,"vipStatus":1,"vipStatusWarn":""},"fans_detail":null,"following":0},"content":{"message":"hey 朋友起来刷无限池了","plat":2,"device":"","members":[]},"replies":null,"assist":0,"folder":{"has_folded":false,"is_folded":false,"rule":"https://www.bilibili.com/blackboard/foldingreply.html"}},{"rpid":1311722276,"oid":41025837,"type":1,"mid":7889887,"root":0,"parent":0,"dialog":0,"count":0,"rcount":0,"floor":1054,"state":2,"fansgrade":0,"attr":8,"ctime":1547798883,"rpid_str":"1311722276","root_str":"0","parent_str":"0","dialog_str":"","like":0,"action":0,"member":{"mid":"7889887","uname":"新东方仗助","sex":"女","sign":"EL PSY CONGROO","avatar":"http://i0.hdslb.com/bfs/face/5c9c5cffda236482186b0b2a361f57d9b8cd0d50.jpg","rank":"10000","DisplayRank":"0","level_info":{"current_level":5,"current_min":0,"current_exp":0,"next_exp":0},"pendant":{"pid":0,"name":"","image":"","expire":0},"nameplate":{"nid":0,"name":"","image":"","image_small":"","level":"","condition":""},"official_verify":{"type":-1,"desc":""},"vip":{"vipType":2,"vipDueDate":1570809600000,"dueRemark":"","accessStatus":0,"vipStatus":1,"vipStatusWarn":""},"fans_detail":null,"following":0},"content":{"message":"泛式真**是个天才","plat":2,"device":"","members":[]},"replies":null,"assist":0,"folder":{"has_folded":false,"is_folded":false,"rule":"https://www.bilibili.com/blackboard/foldingreply.html"}},{"rpid":1311759348,"oid":41025837,"type":1,"mid":14704901,"root":0,"parent":0,"dialog":0,"count":0,"rcount":0,"floor":1052,"state":0,"fansgrade":0,"attr":0,"ctime":1547798864,"rpid_str":"1311759348","root_str":"0","parent_str":"0","dialog_str":"","like":0,"action":0,"member":{"mid":"14704901","uname":"banana天下第一","sex":"保密","sign":"","avatar":"http://i0.hdslb.com/bfs/face/aaa91a50f7fd477fb2124da68bf44f8d580196fe.jpg","rank":"10000","DisplayRank":"0","level_info":{"current_level":4,"current_min":0,"current_exp":0,"next_exp":0},"pendant":{"pid":0,"name":"","image":"","expire":0},"nameplate":{"nid":0,"name":"","image":"","image_small":"","level":"","condition":""},"official_verify":{"type":-1,"desc":""},"vip":{"vipType":1,"vipDueDate":1550246400000,"dueRemark":"","accessStatus":0,"vipStatus":1,"vipStatusWarn":""},"fans_detail":null,"following":0},"content":{"message":"约书亚不是死于弹片而且后面的战争吧，虽然动画里没有[蛆音娘_吃瓜群众]","plat":2,"device":"","members":[]},"replies":null,"assist":0,"folder":{"has_folded":false,"is_folded":false,"rule":"https://www.bilibili.com/blackboard/foldingreply.html"}},{"rpid":1311758344,"oid":41025837,"type":1,"mid":34004061,"root":0,"parent":0,"dialog":0,"count":0,"rcount":0,"floor":1051,"state":0,"fansgrade":1,"attr":0,"ctime":1547798819,"rpid_str":"1311758344","root_str":"0","parent_str":"0","dialog_str":"","like":2,"action":0,"member":{"mid":"34004061","uname":"自由-_-星空","sex":"男","sign":"我永远喜欢古河渚和忍野忍.JPG","avatar":"http://i2.hdslb.com/bfs/face/caa9fbafc6d62251607b03a0622390102adace4f.jpg","rank":"10000","DisplayRank":"0","level_info":{"current_level":5,"current_min":0,"current_exp":0,"next_exp":0},"pendant":{"pid":215,"name":"木之本樱","image":"http://i0.hdslb.com/bfs/face/ce53b1783a7fe43998abc1a807e5a37aa3548933.png","expire":1569465112},"nameplate":{"nid":0,"name":"","image":"","image_small":"","level":"","condition":""},"official_verify":{"type":-1,"desc":""},"vip":{"vipType":2,"vipDueDate":1601308800000,"dueRemark":"","accessStatus":0,"vipStatus":1,"vipStatusWarn":""},"fans_detail":{"uid":34004061,"medal_id":2226,"medal_name":"泛团","score":0,"level":1,"intimacy":0,"master_status":1,"is_receive":1},"following":0},"content":{"message":"你看这个柯尼，都六岁了分还这么低，不如我们把她出货了吧","plat":2,"device":"","members":[]},"replies":null,"assist":0,"folder":{"has_folded":false,"is_folded":false,"rule":"https://www.bilibili.com/blackboard/foldingreply.html"}},{"rpid":1311757934,"oid":41025837,"type":1,"mid":5222101,"root":0,"parent":0,"dialog":0,"count":0,"rcount":0,"floor":1050,"state":0,"fansgrade":0,"attr":0,"ctime":1547798800,"rpid_str":"1311757934","root_str":"0","parent_str":"0","dialog_str":"","like":0,"action":0,"member":{"mid":"5222101","uname":"抱走勇贵的BBQ","sex":"女","sign":"最近打工，要下个月才能做点视频","avatar":"http://i0.hdslb.com/bfs/face/85b80f3b7e68d87e8292768bff86dae62f13cf8b.jpg","rank":"10000","DisplayRank":"0","level_info":{"current_level":5,"current_min":0,"current_exp":0,"next_exp":0},"pendant":{"pid":278,"name":"中野五月","image":"http://i1.hdslb.com/bfs/face/ae0a1be49f84a710ff643145580e0786727adb33.png","expire":1548435222},"nameplate":{"nid":74,"name":"大会员2018年度勋章","image":"http://i2.hdslb.com/bfs/face/421179426c929dfeaed4117461c83f5d07ffb148.png","image_small":"http://i0.hdslb.com/bfs/face/682001c2e1c2ae887bdf2a0e18eef61180c48f84.png","level":"稀有勋章","condition":"2018.6.26-7.8某一天是年度大会员"},"official_verify":{"type":-1,"desc":""},"vip":{"vipType":2,"vipDueDate":1553184000000,"dueRemark":"","accessStatus":0,"vipStatus":1,"vipStatusWarn":""},"fans_detail":null,"following":0},"content":{"message":"五月天！五月天！","plat":1,"device":"","members":[]},"replies":null,"assist":0,"folder":{"has_folded":false,"is_folded":false,"rule":"https://www.bilibili.com/blackboard/foldingreply.html"}},{"rpid":1311722080,"oid":41025837,"type":1,"mid":2965888,"root":0,"parent":0,"dialog":0,"count":0,"rcount":0,"floor":1049,"state":0,"fansgrade":0,"attr":0,"ctime":1547798783,"rpid_str":"1311722080","root_str":"0","parent_str":"0","dialog_str":"","like":0,"action":0,"member":{"mid":"2965888","uname":"EFvirgil","sex":"保密","sign":"","avatar":"http://i2.hdslb.com/bfs/face/7009187db513283d66c11bf93b1eee006c2c256f.jpg","rank":"10000","DisplayRank":"0","level_info":{"current_level":5,"current_min":0,"current_exp":0,"next_exp":0},"pendant":{"pid":0,"name":"","image":"","expire":0},"nameplate":{"nid":0,"name":"","image":"","image_small":"","level":"","condition":""},"official_verify":{"type":-1,"desc":""},"vip":{"vipType":2,"vipDueDate":1554652800000,"dueRemark":"","accessStatus":0,"vipStatus":1,"vipStatusWarn":""},"fans_detail":null,"following":0},"content":{"message":"一色天下第一，老师是天。。。不好意思走错了[2233娘_大笑]","plat":2,"device":"","members":[]},"replies":null,"assist":0,"folder":{"has_folded":false,"is_folded":false,"rule":"https://www.bilibili.com/blackboard/foldingreply.html"}},{"rpid":1311756125,"oid":41025837,"type":1,"mid":345191751,"root":0,"parent":0,"dialog":0,"count":0,"rcount":0,"floor":1048,"state":0,"fansgrade":0,"attr":0,"ctime":1547798719,"rpid_str":"1311756125","root_str":"0","parent_str":"0","dialog_str":"","like":0,"action":0,"member":{"mid":"345191751","uname":"ZUN已在我床上","sex":"保密","sign":"改签名要硬币么？\nつまらない","avatar":"http://i0.hdslb.com/bfs/face/1391a740449f4d89c948a631cb731201e71f59b0.jpg","rank":"10000","DisplayRank":"0","level_info":{"current_level":3,"current_min":0,"current_exp":0,"next_exp":0},"pendant":{"pid":105,"name":"纳米核心","image":"http://i0.hdslb.com/bfs/face/b67a37542d33d093ff28780848448e0a1c78932a.png","expire":1582128000},"nameplate":{"nid":0,"name":"","image":"","image_small":"","level":"","condition":""},"official_verify":{"type":-1,"desc":""},"vip":{"vipType":2,"vipDueDate":1582128000000,"dueRemark":"","accessStatus":0,"vipStatus":1,"vipStatusWarn":""},"fans_detail":null,"following":0},"content":{"message":"没看，流量不允许","plat":2,"device":"","members":[]},"replies":null,"assist":0,"folder":{"has_folded":false,"is_folded":false,"rule":"https://www.bilibili.com/blackboard/foldingreply.html"}},{"rpid":1311755971,"oid":41025837,"type":1,"mid":104968,"root":0,"parent":0,"dialog":0,"count":0,"rcount":0,"floor":1047,"state":0,"fansgrade":0,"attr":0,"ctime":1547798712,"rpid_str":"1311755971","root_str":"0","parent_str":"0","dialog_str":"","like":0,"action":0,"member":{"mid":"104968","uname":"suzumiyayoung","sex":"保密","sign":"傳失敗的頭像,有時候也別有一番風味","avatar":"http://i2.hdslb.com/bfs/face/f19486f8639cfbc01d8b2f8bfd7f5968e73ee752.gif","rank":"10000","DisplayRank":"0","level_info":{"current_level":5,"current_min":0,"current_exp":0,"next_exp":0},"pendant":{"pid":196,"name":"梦100","image":"http://i1.hdslb.com/bfs/face/d3587e6f3b534499fc08a71296bafa74a159fa33.png","expire":1570118400},"nameplate":{"nid":61,"name":"饭圈楷模","image":"http://i2.hdslb.com/bfs/face/5a90f715451325c642a6ac39e01195cb6d075734.png","image_small":"http://i2.hdslb.com/bfs/face/5bfc1b4fb3f4b411495dddb0b2127ad80f6fbcac.png","level":"普通勋章","condition":"当前持有粉丝勋章最高等级\u003e=10级"},"official_verify":{"type":-1,"desc":""},"vip":{"vipType":2,"vipDueDate":1570118400000,"dueRemark":"","accessStatus":0,"vipStatus":1,"vipStatusWarn":""},"fans_detail":null,"following":0},"content":{"message":"泛式原來你還記得mad怎麼做的麼","plat":1,"device":"","members":[]},"replies":null,"assist":0,"folder":{"has_folded":false,"is_folded":false,"rule":"https://www.bilibili.com/blackboard/foldingreply.html"}},{"rpid":1311721926,"oid":41025837,"type":1,"mid":1577158,"root":0,"parent":0,"dialog":0,"count":0,"rcount":0,"floor":1046,"state":0,"fansgrade":0,"attr":0,"ctime":1547798699,"rpid_str":"1311721926","root_str":"0","parent_str":"0","dialog_str":"","like":2,"action":0,"member":{"mid":"1577158","uname":"看穿一切的兔","sex":"男","sign":"手动玩家一枚，B2服","avatar":"http://i1.hdslb.com/bfs/face/8a1fc1e263b751eda854f4b4159d70d71a580e5b.jpg","rank":"10000","DisplayRank":"0","level_info":{"current_level":6,"current_min":0,"current_exp":0,"next_exp":0},"pendant":{"pid":0,"name":"","image":"","expire":0},"nameplate":{"nid":0,"name":"","image":"","image_small":"","level":"","condition":""},"official_verify":{"type":-1,"desc":""},"vip":{"vipType":2,"vipDueDate":1571414400000,"dueRemark":"","accessStatus":0,"vipStatus":1,"vipStatusWarn":""},"fans_detail":null,"following":0},"content":{"message":"旋风游侠使用技能:旋风更新","plat":2,"device":"","members":[]},"replies":null,"assist":0,"folder":{"has_folded":false,"is_folded":false,"rule":"https://www.bilibili.com/blackboard/foldingreply.html"}},{"rpid":1311739087,"oid":41025837,"type":1,"mid":26195149,"root":0,"parent":0,"dialog":0,"count":0,"rcount":0,"floor":1045,"state":0,"fansgrade":0,"attr":0,"ctime":1547798694,"rpid_str":"1311739087","root_str":"0","parent_str":"0","dialog_str":"","like":0,"action":0,"member":{"mid":"26195149","uname":"名字中透出一股欧气","sex":"男","sign":"","avatar":"http://i2.hdslb.com/bfs/face/df034fda904d768636273c2274d81a6c409bac84.jpg","rank":"10000","DisplayRank":"0","level_info":{"current_level":4,"current_min":0,"current_exp":0,"next_exp":0},"pendant":{"pid":233,"name":"刺客伍六七","image":"http://i1.hdslb.com/bfs/face/b8a480b0f74935ca3146975f6591346d888669e3.png","expire":1570809600},"nameplate":{"nid":0,"name":"","image":"","image_small":"","level":"","condition":""},"official_verify":{"type":-1,"desc":""},"vip":{"vipType":2,"vipDueDate":1570809600000,"dueRemark":"","accessStatus":0,"vipStatus":1,"vipStatusWarn":""},"fans_detail":null,"following":0},"content":{"message":"泛式这期好好玩，好久没看过这么有意思的了[小电视_我好兴奋]","plat":2,"device":"","members":[]},"replies":null,"assist":0,"folder":{"has_folded":false,"is_folded":false,"rule":"https://www.bilibili.com/blackboard/foldingreply.html"}},{"rpid":1311721910,"oid":41025837,"type":1,"mid":86747695,"root":0,"parent":0,"dialog":0,"count":0,"rcount":0,"floor":1044,"state":0,"fansgrade":1,"attr":0,"ctime":1547798688,"rpid_str":"1311721910","root_str":"0","parent_str":"0","dialog_str":"","like":0,"action":0,"member":{"mid":"86747695","uname":"百家青衿","sex":"保密","sign":"隐荣华，自飒沓\n拂衣去，任逍遥\n千年儒裳，百家青衿","avatar":"http://i1.hdslb.com/bfs/face/ab8da28df13a63bd21896cf4c7ca5e91142cc737.jpg","rank":"10000","DisplayRank":"0","level_info":{"current_level":4,"current_min":0,"current_exp":0,"next_exp":0},"pendant":{"pid":0,"name":"","image":"","expire":0},"nameplate":{"nid":0,"name":"","image":"","image_small":"","level":"","condition":""},"official_verify":{"type":-1,"desc":""},"vip":{"vipType":0,"vipDueDate":0,"dueRemark":"","accessStatus":0,"vipStatus":0,"vipStatusWarn":""},"fans_detail":{"uid":86747695,"medal_id":2226,"medal_name":"泛团","score":0,"level":2,"intimacy":0,"master_status":1,"is_receive":1},"following":0},"content":{"message":"不会做MAD的杂谈up主不是好的女装大佬","plat":2,"device":"","members":[]},"replies":null,"assist":0,"folder":{"has_folded":false,"is_folded":false,"rule":"https://www.bilibili.com/blackboard/foldingreply.html"}},{"rpid":1311721863,"oid":41025837,"type":1,"mid":4451813,"root":0,"parent":0,"dialog":0,"count":0,"rcount":0,"floor":1043,"state":0,"fansgrade":0,"attr":0,"ctime":1547798664,"rpid_str":"1311721863","root_str":"0","parent_str":"0","dialog_str":"","like":0,"action":0,"member":{"mid":"4451813","uname":"克鲁特的小花","sex":"男","sign":"小姐姐要以身相许么~~~我可是勇者呀~！","avatar":"http://i2.hdslb.com/bfs/face/0fc6e058b399bfa5fd92192751291620ddc6c12e.jpg","rank":"10000","DisplayRank":"0","level_info":{"current_level":5,"current_min":0,"current_exp":0,"next_exp":0},"pendant":{"pid":236,"name":"沈剑心","image":"http://i2.hdslb.com/bfs/face/b9eba4944ec9c2d2f7d60f38f90b4487136832ff.png","expire":1570982400},"nameplate":{"nid":0,"name":"","image":"","image_small":"","level":"","condition":""},"official_verify":{"type":-1,"desc":""},"vip":{"vipType":2,"vipDueDate":1570982400000,"dueRemark":"","accessStatus":0,"vipStatus":1,"vipStatusWarn":""},"fans_detail":null,"following":0},"content":{"message":"泛式四叶党\n瓶子五月党","plat":1,"device":"","members":[]},"replies":null,"assist":0,"folder":{"has_folded":false,"is_folded":false,"rule":"https://www.bilibili.com/blackboard/foldingreply.html"}},{"rpid":1311754313,"oid":41025837,"type":1,"mid":4424422,"root":0,"parent":0,"dialog":0,"count":0,"rcount":0,"floor":1042,"state":0,"fansgrade":0,"attr":0,"ctime":1547798631,"rpid_str":"1311754313","root_str":"0","parent_str":"0","dialog_str":"","like":14,"action":0,"member":{"mid":"4424422","uname":"背锅达人王霸霸","sex":"男","sign":"","avatar":"http://i2.hdslb.com/bfs/face/440e640b59f92c76615cbb7563b488e697b1dd55.jpg","rank":"10000","DisplayRank":"0","level_info":{"current_level":5,"current_min":0,"current_exp":0,"next_exp":0},"pendant":{"pid":133,"name":"斗破苍穹","image":"http://i1.hdslb.com/bfs/face/aa19084c7da60e464e2b8b651a626eb8a75326fa.png","expire":1571414400},"nameplate":{"nid":0,"name":"","image":"","image_small":"","level":"","condition":""},"official_verify":{"type":-1,"desc":""},"vip":{"vipType":2,"vipDueDate":1571414400000,"dueRemark":"","accessStatus":0,"vipStatus":1,"vipStatusWarn":""},"fans_detail":null,"following":0},"content":{"message":"？不去做mod扬名立万 窝在这里当个杂谈小up？","plat":2,"device":"","members":[]},"replies":null,"assist":0,"folder":{"has_folded":false,"is_folded":false,"rule":"https://www.bilibili.com/blackboard/foldingreply.html"}},{"rpid":1311754227,"oid":41025837,"type":1,"mid":29833926,"root":0,"parent":0,"dialog":0,"count":0,"rcount":0,"floor":1041,"state":0,"fansgrade":0,"attr":0,"ctime":1547798626,"rpid_str":"1311754227","root_str":"0","parent_str":"0","dialog_str":"","like":0,"action":0,"member":{"mid":"29833926","uname":"思如丧","sex":"保密","sign":"冷到切骨","avatar":"http://i1.hdslb.com/bfs/face/eebd148ece6c8f8ad7149f66028530d7869b5632.jpg","rank":"10000","DisplayRank":"0","level_info":{"current_level":4,"current_min":0,"current_exp":0,"next_exp":0},"pendant":{"pid":134,"name":"天谕","image":"http://i0.hdslb.com/bfs/face/0fe85df67146df20b558a38d6fc2a72d3657b1fe.png","expire":1570809600},"nameplate":{"nid":0,"name":"","image":"","image_small":"","level":"","condition":""},"official_verify":{"type":-1,"desc":""},"vip":{"vipType":2,"vipDueDate":1570809600000,"dueRemark":"","accessStatus":0,"vipStatus":1,"vipStatusWarn":""},"fans_detail":null,"following":0},"content":{"message":"真的牛批","plat":2,"device":"","members":[]},"replies":null,"assist":0,"folder":{"has_folded":false,"is_folded":false,"rule":"https://www.bilibili.com/blackboard/foldingreply.html"}},{"rpid":1311754071,"oid":41025837,"type":1,"mid":9191202,"root":0,"parent":0,"dialog":0,"count":0,"rcount":0,"floor":1040,"state":0,"fansgrade":0,"attr":0,"ctime":1547798618,"rpid_str":"1311754071","root_str":"0","parent_str":"0","dialog_str":"","like":0,"action":0,"member":{"mid":"9191202","uname":"黑黑的王子","sex":"保密","sign":"","avatar":"http://i0.hdslb.com/bfs/face/edfa2df37620bfe1e1ae5ad4746b0a0ba4591251.jpg","rank":"10000","DisplayRank":"0","level_info":{"current_level":5,"current_min":0,"current_exp":0,"next_exp":0},"pendant":{"pid":107,"name":"全职高手","image":"http://i0.hdslb.com/bfs/face/4fade9d625b7b2b8cadbd93106c1f10457e131c3.png","expire":1552665600},"nameplate":{"nid":74,"name":"大会员2018年度勋章","image":"http://i0.hdslb.com/bfs/face/421179426c929dfeaed4117461c83f5d07ffb148.png","image_small":"http://i1.hdslb.com/bfs/face/682001c2e1c2ae887bdf2a0e18eef61180c48f84.png","level":"稀有勋章","condition":"2018.6.26-7.8某一天是年度大会员"},"official_verify":{"type":-1,"desc":""},"vip":{"vipType":2,"vipDueDate":1589644800000,"dueRemark":"","accessStatus":0,"vipStatus":1,"vipStatusWarn":""},"fans_detail":null,"following":0},"content":{"message":"佐仓绫音天下第一（破音）","plat":2,"device":"","members":[]},"replies":null,"assist":0,"folder":{"has_folded":false,"is_folded":false,"rule":"https://www.bilibili.com/blackboard/foldingreply.html"}}],"top":null,"upper":{"mid":63231,"top":{"rpid":1311623686,"oid":41025837,"type":1,"mid":12266280,"root":0,"parent":0,"dialog":0,"count":190,"rcount":187,"floor":767,"state":0,"fansgrade":1,"attr":2,"ctime":1547793613,"rpid_str":"1311623686","root_str":"0","parent_str":"0","dialog_str":"","like":4676,"action":0,"member":{"mid":"12266280","uname":"剑之骑士","sex":"男","sign":"抱着阿比等阿荣","avatar":"http://i2.hdslb.com/bfs/face/40744cf3852e2af2161504daacf3ae6034e5d425.jpg","rank":"10000","DisplayRank":"0","level_info":{"current_level":6,"current_min":0,"current_exp":0,"next_exp":0},"pendant":{"pid":0,"name":"","image":"","expire":0},"nameplate":{"nid":57,"name":"收集萌新","image":"http://i0.hdslb.com/bfs/face/7767275600ea63d351b22fa87ec15a79aa24e5e5.png","image_small":"http://i2.hdslb.com/bfs/face/6589d992655595bf51543f268040eaeaed372fae.png","level":"普通勋章","condition":"同时拥有粉丝勋章\u003e=5个"},"official_verify":{"type":-1,"desc":""},"vip":{"vipType":2,"vipDueDate":1610985600000,"dueRemark":"","accessStatus":0,"vipStatus":1,"vipStatusWarn":""},"fans_detail":{"uid":12266280,"medal_id":2226,"medal_name":"泛团","score":0,"level":6,"intimacy":0,"master_status":1,"is_receive":1},"following":0},"content":{"message":"泛式是四叶党，因为他从出生开始就单推佐仓绫音了","plat":2,"device":"","members":[]},"replies":[{"rpid":1311593397,"oid":41025837,"type":1,"mid":2070485,"root":1311623686,"parent":1311623686,"dialog":1311593397,"count":0,"rcount":0,"floor":1,"state":0,"fansgrade":0,"attr":0,"ctime":1547793970,"rpid_str":"1311593397","root_str":"1311623686","parent_str":"1311623686","dialog_str":"","like":118,"action":0,"member":{"mid":"2070485","uname":"绅士之友","sex":"男","sign":"别看了，没啥好看的","avatar":"http://i2.hdslb.com/bfs/face/e364826ef7317ad9066ad821b1fa1af2b3415ff4.jpg","rank":"10000","DisplayRank":"0","level_info":{"current_level":5,"current_min":0,"current_exp":0,"next_exp":0},"pendant":{"pid":0,"name":"","image":"","expire":0},"nameplate":{"nid":0,"name":"","image":"","image_small":"","level":"","condition":""},"official_verify":{"type":-1,"desc":""},"vip":{"vipType":2,"vipDueDate":1597680000000,"dueRemark":"","accessStatus":0,"vipStatus":1,"vipStatusWarn":""},"fans_detail":null,"following":0},"content":{"message":"四叶党集合啦(=・ω・=)","plat":2,"device":"","members":[]},"replies":null,"assist":0,"folder":{"has_folded":false,"is_folded":false,"rule":""}},{"rpid":1311558946,"oid":41025837,"type":1,"mid":20635614,"root":1311623686,"parent":1311623686,"dialog":1311558946,"count":0,"rcount":0,"floor":2,"state":0,"fansgrade":1,"attr":0,"ctime":1547793975,"rpid_str":"1311558946","root_str":"1311623686","parent_str":"1311623686","dialog_str":"","like":214,"action":0,"member":{"mid":"20635614","uname":"非の咸鱼","sex":"保密","sign":" ","avatar":"http://i0.hdslb.com/bfs/face/37aaf37b18c372165c40ed1fb5e83a296c9c5587.jpg","rank":"10000","DisplayRank":"0","level_info":{"current_level":5,"current_min":0,"current_exp":0,"next_exp":0},"pendant":{"pid":212,"name":"冲出太阳系","image":"http://i0.hdslb.com/bfs/face/550ab04740b1779e0da966ede9e17f3231405530.png","expire":1571045738},"nameplate":{"nid":61,"name":"饭圈楷模","image":"http://i1.hdslb.com/bfs/face/5a90f715451325c642a6ac39e01195cb6d075734.png","image_small":"http://i2.hdslb.com/bfs/face/5bfc1b4fb3f4b411495dddb0b2127ad80f6fbcac.png","level":"普通勋章","condition":"当前持有粉丝勋章最高等级\u003e=10级"},"official_verify":{"type":-1,"desc":""},"vip":{"vipType":1,"vipDueDate":1529510400000,"dueRemark":"","accessStatus":0,"vipStatus":0,"vipStatusWarn":""},"fans_detail":{"uid":20635614,"medal_id":2226,"medal_name":"泛团","score":0,"level":1,"intimacy":0,"master_status":1,"is_receive":1},"following":0},"content":{"message":"你又出生了？停止你的dd行为","plat":2,"device":"","members":[]},"replies":null,"assist":0,"folder":{"has_folded":false,"is_folded":false,"rule":""}},{"rpid":1311632395,"oid":41025837,"type":1,"mid":34076948,"root":1311623686,"parent":1311623686,"dialog":1311632395,"count":0,"rcount":0,"floor":3,"state":0,"fansgrade":0,"attr":0,"ctime":1547793976,"rpid_str":"1311632395","root_str":"1311623686","parent_str":"1311623686","dialog_str":"","like":282,"action":0,"member":{"mid":"34076948","uname":"僮話の影孞","sex":"保密","sign":"咸鱼up,主七都/bvn制作,不定期更新 企鹅:2216220403 ","avatar":"http://i1.hdslb.com/bfs/face/f3635fbc001717ee8fd7bfc9809ac5ee448bb059.jpg","rank":"10000","DisplayRank":"0","level_info":{"current_level":4,"current_min":0,"current_exp":0,"next_exp":0},"pendant":{"pid":0,"name":"","image":"","expire":0},"nameplate":{"nid":4,"name":"青铜殿堂","image":"http://i0.hdslb.com/bfs/face/2879cd5fb8518f7c6da75887994c1b2a7fe670bd.png","image_small":"http://i1.hdslb.com/bfs/face/6707c120e00a3445933308fd9b7bd9fad99e9ec4.png","level":"普通勋章","condition":"单个自制视频总播放数\u003e=1万"},"official_verify":{"type":-1,"desc":""},"vip":{"vipType":0,"vipDueDate":0,"dueRemark":"","accessStatus":0,"vipStatus":0,"vipStatusWarn":""},"fans_detail":null,"following":0},"content":{"message":"被置顶了才是最骚的","plat":2,"device":"","members":[]},"replies":null,"assist":0,"folder":{"has_folded":false,"is_folded":false,"rule":""}}],"assist":0,"folder":{"has_folded":false,"is_folded":false,"rule":"https://www.bilibili.com/blackboard/foldingreply.html"}}}}}